term_printer/__init__.py
term_printer/consts/__init__.py
term_printer/consts/color.py
term_printer/consts/format.py
term_printer/objects/__init__.py
term_printer/objects/std_text.py
tests/__init__.py
tests/test_print.py
term_printer-1.1.dist-info/LICENSE
term_printer-1.1.dist-info/METADATA
term_printer-1.1.dist-info/WHEEL
term_printer-1.1.dist-info/top_level.txt
term_printer-1.1.dist-info/RECORD
