Metadata-Version: 2.1
Name: term-printer
Version: 1.1
Summary: Print 'text color' and 'text format' on Term with Python
Home-page: https://github.com/nanato12/term-printer
Author: nanato12
Author-email: admin@nanato12.info
License: Apache License 2.0
Keywords: term-color term-format color-print print-color
Platform: UNKNOWN
Classifier: License :: OSI Approved :: Apache Software License
Classifier: Programming Language :: Python :: 3
Classifier: Programming Language :: Python :: 3 :: Only
Classifier: Programming Language :: Python :: 3.6
Classifier: Programming Language :: Python :: 3.7
Classifier: Programming Language :: Python :: 3.8
Classifier: Programming Language :: Python :: 3.9
Requires-Python: >=3.6
